{
  "parent": "minecraft:recipes/root",
  "rewards": {
    "recipes": [
      "galacticraftcore:ambient_thermal_controller"
    ]
  },
  "criteria": {
    "has_wafers/basic_tag": {
      "trigger": "minecraft:inventory_changed",
      "conditions": {
        "items": [
          {
            "tag": "forge:wafers/basic"
          }
        ]
      }
    },
    "has_the_recipe": {
      "trigger": "minecraft:recipe_unlocked",
      "conditions": {
        "recipe": "galacticraftcore:ambient_thermal_controller"
      }
    }
  },
  "requirements": [
    [
      "has_wafers/basic_tag",
      "has_the_recipe"
    ]
  ]
}